fqe/__init__.py
fqe/_fqe_control.py
fqe/_version.py
fqe/bitstring.py
fqe/cirq_utils.py
fqe/fci_graph.py
fqe/fci_graph_set.py
fqe/fqe_data.py
fqe/fqe_data_set.py
fqe/fqe_decorators.py
fqe/openfermion_utils.py
fqe/settings.py
fqe/transform.py
fqe/util.py
fqe/wavefunction.py
fqe/wick.py
fqe/algorithm/__init__.py
fqe/algorithm/adapt_vqe.py
fqe/algorithm/algorithm_util.py
fqe/algorithm/brillouin_calculator.py
fqe/algorithm/brillouin_condition_solver.py
fqe/algorithm/davidson.py
fqe/algorithm/generalized_doubles_factorization.py
fqe/algorithm/low_rank.py
fqe/algorithm/low_rank_api.py
fqe/algorithm/vbc.py
fqe/fqe_ops/__init__.py
fqe/fqe_ops/fqe_operator.py
fqe/fqe_ops/fqe_ops.py
fqe/fqe_ops/fqe_ops_utils.py
fqe/hamiltonians/__init__.py
fqe/hamiltonians/diagonal_coulomb.py
fqe/hamiltonians/diagonal_hamiltonian.py
fqe/hamiltonians/general_hamiltonian.py
fqe/hamiltonians/gso_hamiltonian.py
fqe/hamiltonians/hamiltonian.py
fqe/hamiltonians/hamiltonian_utils.py
fqe/hamiltonians/restricted_hamiltonian.py
fqe/hamiltonians/sparse_hamiltonian.py
fqe/hamiltonians/sso_hamiltonian.py
fqe/lib/__init__.py
fqe/lib/bitstring.py
fqe/lib/cirq_utils.py
fqe/lib/fci_graph.py
fqe/lib/fqe_data.so
fqe/lib/libfqe.so
fqe/lib/linalg.py
fqe/lib/wick.py
fqe/tensor/__init__.py
fqe/tensor/tensor_utils.py
fqe-0.3.0.dist-info/LICENSE
fqe-0.3.0.dist-info/METADATA
fqe-0.3.0.dist-info/WHEEL
fqe-0.3.0.dist-info/top_level.txt
fqe-0.3.0.dist-info/RECORD
