Metadata-Version: 2.1
Name: fqe
Version: 0.3.0
Summary: OpenFermion Fermionic Quantum Emulator
Home-page: http://www.openfermion.org
Author: The OpenFermion FQE Developers
Author-email: help@openfermion.org
License: Apache 2
License-File: LICENSE
Requires-Dist: openfermion (>=1.5.0)
Requires-Dist: cirq-core (>=0.15.0)
Requires-Dist: cirq-google (>=0.15.0)
Requires-Dist: jupyter
Requires-Dist: numpy (>=1.14)
Requires-Dist: scipy
Requires-Dist: pyasn1-modules (==0.2.7)
Requires-Dist: Sphinx (>=2.3.1)
Requires-Dist: Cython
